fsspec_xrootd/__init__.py
fsspec_xrootd/_version.py
fsspec_xrootd/_version.pyi
fsspec_xrootd/py.typed
fsspec_xrootd/xrootd.py
fsspec_xrootd-0.5.0.dist-info/LICENSE
fsspec_xrootd-0.5.0.dist-info/METADATA
fsspec_xrootd-0.5.0.dist-info/WHEEL
fsspec_xrootd-0.5.0.dist-info/entry_points.txt
fsspec_xrootd-0.5.0.dist-info/top_level.txt
fsspec_xrootd-0.5.0.dist-info/RECORD
