Metadata-Version: 2.2
Name: fsspec_xrootd
Version: 0.5.0
Summary: xrootd implementation for fsspec
Home-page: https://github.com/CoffeaTeam/fsspec-xrootd
Author: Scott Demarest
Author-email: rockets1194@gmail.com
Maintainer: CoffeaTeam admins
Maintainer-email: rockets1194@gmail.com
License: BSD-3-Clause
Project-URL: Documentation, https://fsspec_xrootd.readthedocs.io/
Project-URL: Bug Tracker, https://github.com/CoffeaTeam/fsspec-xrootd/issues
Project-URL: Discussions, https://github.com/CoffeaTeam/fsspec-xrootd/discussions
Project-URL: Changelog, https://github.com/CoffeaTeam/fsspec-xrootd/releases
Platform: Any
Classifier: Development Status :: 1 - Planning
Classifier: Intended Audience :: Developers
Classifier: Intended Audience :: Science/Research
Classifier: License :: OSI Approved :: BSD License
Classifier: Operating System :: OS Independent
Classifier: Programming Language :: Python
Classifier: Programming Language :: Python :: 3
Classifier: Programming Language :: Python :: 3 :: Only
Classifier: Topic :: Scientific/Engineering
Requires-Python: >=3.9
License-File: LICENSE
Requires-Dist: fsspec
Provides-Extra: dev
Requires-Dist: pytest>=6; extra == "dev"
Provides-Extra: docs
Requires-Dist: Sphinx>=4.0; extra == "docs"
Requires-Dist: myst-parser>=0.13; extra == "docs"
Requires-Dist: sphinx-book-theme>=0.1.0; extra == "docs"
Requires-Dist: sphinx-copybutton; extra == "docs"
Provides-Extra: test
Requires-Dist: pytest>=6; extra == "test"
Requires-Dist: pytest-rerunfailures; extra == "test"
Requires-Dist: pytest-timeout; extra == "test"
